[
  {
    "ContainingType": "NeoFilm.Backend.Controllers.BillController",
    "Method": "GetAsync",
    "RelativePath": "api/Bill",
    "HttpMethod": "GET",
    "IsController": true,
    "Order": 0,
    "Parameters": [],
    "ReturnTypes": []
  },
  {
    "ContainingType": "NeoFilm.Backend.Controllers.GenericController\u00601[[NeoFilm.Shared.Entities.Bill, NeoFilm.Shared, Version=1.0.0.0, Culture=neutral, PublicKeyToken=null]]",
    "Method": "PostAsync",
    "RelativePath": "api/Bill",
    "HttpMethod": "POST",
    "IsController": true,
    "Order": 0,
    "Parameters": [
      {
        "Name": "model",
        "Type": "NeoFilm.Shared.Entities.Bill",
        "IsRequired": true
      }
    ],
    "ReturnTypes": []
  },
  {
    "ContainingType": "NeoFilm.Backend.Controllers.GenericController\u00601[[NeoFilm.Shared.Entities.Bill, NeoFilm.Shared, Version=1.0.0.0, Culture=neutral, PublicKeyToken=null]]",
    "Method": "PutAsync",
    "RelativePath": "api/Bill",
    "HttpMethod": "PUT",
    "IsController": true,
    "Order": 0,
    "Parameters": [
      {
        "Name": "model",
        "Type": "NeoFilm.Shared.Entities.Bill",
        "IsRequired": true
      }
    ],
    "ReturnTypes": []
  },
  {
    "ContainingType": "NeoFilm.Backend.Controllers.BillController",
    "Method": "GetAsync",
    "RelativePath": "api/Bill/{id}",
    "HttpMethod": "GET",
    "IsController": true,
    "Order": 0,
    "Parameters": [
      {
        "Name": "id",
        "Type": "System.Int32",
        "IsRequired": true
      }
    ],
    "ReturnTypes": []
  },
  {
    "ContainingType": "NeoFilm.Backend.Controllers.GenericController\u00601[[NeoFilm.Shared.Entities.Bill, NeoFilm.Shared, Version=1.0.0.0, Culture=neutral, PublicKeyToken=null]]",
    "Method": "DeleteAsync",
    "RelativePath": "api/Bill/{id}",
    "HttpMethod": "DELETE",
    "IsController": true,
    "Order": 0,
    "Parameters": [
      {
        "Name": "id",
        "Type": "System.Int32",
        "IsRequired": true
      }
    ],
    "ReturnTypes": []
  },
  {
    "ContainingType": "NeoFilm.Backend.Controllers.BillController",
    "Method": "Create",
    "RelativePath": "api/Bill/create",
    "HttpMethod": "POST",
    "IsController": true,
    "Order": 0,
    "Parameters": [
      {
        "Name": "model",
        "Type": "CreateBillDTO",
        "IsRequired": true
      }
    ],
    "ReturnTypes": []
  },
  {
    "ContainingType": "NeoFilm.Backend.Controllers.CategorieFilmsController",
    "Method": "GetAsync",
    "RelativePath": "api/CategorieFilms",
    "HttpMethod": "GET",
    "IsController": true,
    "Order": 0,
    "Parameters": [],
    "ReturnTypes": []
  },
  {
    "ContainingType": "NeoFilm.Backend.Controllers.GenericController\u00601[[NeoFilm.Shared.Entities.CategorieFilms, NeoFilm.Shared, Version=1.0.0.0, Culture=neutral, PublicKeyToken=null]]",
    "Method": "PostAsync",
    "RelativePath": "api/CategorieFilms",
    "HttpMethod": "POST",
    "IsController": true,
    "Order": 0,
    "Parameters": [
      {
        "Name": "model",
        "Type": "NeoFilm.Shared.Entities.CategorieFilms",
        "IsRequired": true
      }
    ],
    "ReturnTypes": []
  },
  {
    "ContainingType": "NeoFilm.Backend.Controllers.GenericController\u00601[[NeoFilm.Shared.Entities.CategorieFilms, NeoFilm.Shared, Version=1.0.0.0, Culture=neutral, PublicKeyToken=null]]",
    "Method": "PutAsync",
    "RelativePath": "api/CategorieFilms",
    "HttpMethod": "PUT",
    "IsController": true,
    "Order": 0,
    "Parameters": [
      {
        "Name": "model",
        "Type": "NeoFilm.Shared.Entities.CategorieFilms",
        "IsRequired": true
      }
    ],
    "ReturnTypes": []
  },
  {
    "ContainingType": "NeoFilm.Backend.Controllers.CategorieFilmsController",
    "Method": "GetAsync",
    "RelativePath": "api/CategorieFilms/{id}",
    "HttpMethod": "GET",
    "IsController": true,
    "Order": 0,
    "Parameters": [
      {
        "Name": "id",
        "Type": "System.Int32",
        "IsRequired": true
      }
    ],
    "ReturnTypes": []
  },
  {
    "ContainingType": "NeoFilm.Backend.Controllers.GenericController\u00601[[NeoFilm.Shared.Entities.CategorieFilms, NeoFilm.Shared, Version=1.0.0.0, Culture=neutral, PublicKeyToken=null]]",
    "Method": "DeleteAsync",
    "RelativePath": "api/CategorieFilms/{id}",
    "HttpMethod": "DELETE",
    "IsController": true,
    "Order": 0,
    "Parameters": [
      {
        "Name": "id",
        "Type": "System.Int32",
        "IsRequired": true
      }
    ],
    "ReturnTypes": []
  },
  {
    "ContainingType": "NeoFilm.Backend.Controllers.CategorieSnacksController",
    "Method": "GetAsync",
    "RelativePath": "api/CategorieSnacks",
    "HttpMethod": "GET",
    "IsController": true,
    "Order": 0,
    "Parameters": [],
    "ReturnTypes": []
  },
  {
    "ContainingType": "NeoFilm.Backend.Controllers.GenericController\u00601[[NeoFilm.Shared.Entities.CategorieSnacks, NeoFilm.Shared, Version=1.0.0.0, Culture=neutral, PublicKeyToken=null]]",
    "Method": "PostAsync",
    "RelativePath": "api/CategorieSnacks",
    "HttpMethod": "POST",
    "IsController": true,
    "Order": 0,
    "Parameters": [
      {
        "Name": "model",
        "Type": "NeoFilm.Shared.Entities.CategorieSnacks",
        "IsRequired": true
      }
    ],
    "ReturnTypes": []
  },
  {
    "ContainingType": "NeoFilm.Backend.Controllers.GenericController\u00601[[NeoFilm.Shared.Entities.CategorieSnacks, NeoFilm.Shared, Version=1.0.0.0, Culture=neutral, PublicKeyToken=null]]",
    "Method": "PutAsync",
    "RelativePath": "api/CategorieSnacks",
    "HttpMethod": "PUT",
    "IsController": true,
    "Order": 0,
    "Parameters": [
      {
        "Name": "model",
        "Type": "NeoFilm.Shared.Entities.CategorieSnacks",
        "IsRequired": true
      }
    ],
    "ReturnTypes": []
  },
  {
    "ContainingType": "NeoFilm.Backend.Controllers.CategorieSnacksController",
    "Method": "GetAsync",
    "RelativePath": "api/CategorieSnacks/{id}",
    "HttpMethod": "GET",
    "IsController": true,
    "Order": 0,
    "Parameters": [
      {
        "Name": "id",
        "Type": "System.Int32",
        "IsRequired": true
      }
    ],
    "ReturnTypes": []
  },
  {
    "ContainingType": "NeoFilm.Backend.Controllers.GenericController\u00601[[NeoFilm.Shared.Entities.CategorieSnacks, NeoFilm.Shared, Version=1.0.0.0, Culture=neutral, PublicKeyToken=null]]",
    "Method": "DeleteAsync",
    "RelativePath": "api/CategorieSnacks/{id}",
    "HttpMethod": "DELETE",
    "IsController": true,
    "Order": 0,
    "Parameters": [
      {
        "Name": "id",
        "Type": "System.Int32",
        "IsRequired": true
      }
    ],
    "ReturnTypes": []
  },
  {
    "ContainingType": "NeoFilm.Backend.Controllers.DocumentTypeController",
    "Method": "GetAsync",
    "RelativePath": "api/DocumentType",
    "HttpMethod": "GET",
    "IsController": true,
    "Order": 0,
    "Parameters": [],
    "ReturnTypes": []
  },
  {
    "ContainingType": "NeoFilm.Backend.Controllers.GenericController\u00601[[NeoFilm.Shared.Entities.DocumentType, NeoFilm.Shared, Version=1.0.0.0, Culture=neutral, PublicKeyToken=null]]",
    "Method": "PostAsync",
    "RelativePath": "api/DocumentType",
    "HttpMethod": "POST",
    "IsController": true,
    "Order": 0,
    "Parameters": [
      {
        "Name": "model",
        "Type": "NeoFilm.Shared.Entities.DocumentType",
        "IsRequired": true
      }
    ],
    "ReturnTypes": []
  },
  {
    "ContainingType": "NeoFilm.Backend.Controllers.GenericController\u00601[[NeoFilm.Shared.Entities.DocumentType, NeoFilm.Shared, Version=1.0.0.0, Culture=neutral, PublicKeyToken=null]]",
    "Method": "PutAsync",
    "RelativePath": "api/DocumentType",
    "HttpMethod": "PUT",
    "IsController": true,
    "Order": 0,
    "Parameters": [
      {
        "Name": "model",
        "Type": "NeoFilm.Shared.Entities.DocumentType",
        "IsRequired": true
      }
    ],
    "ReturnTypes": []
  },
  {
    "ContainingType": "NeoFilm.Backend.Controllers.DocumentTypeController",
    "Method": "GetAsync",
    "RelativePath": "api/DocumentType/{id}",
    "HttpMethod": "GET",
    "IsController": true,
    "Order": 0,
    "Parameters": [
      {
        "Name": "id",
        "Type": "System.Int32",
        "IsRequired": true
      }
    ],
    "ReturnTypes": []
  },
  {
    "ContainingType": "NeoFilm.Backend.Controllers.GenericController\u00601[[NeoFilm.Shared.Entities.DocumentType, NeoFilm.Shared, Version=1.0.0.0, Culture=neutral, PublicKeyToken=null]]",
    "Method": "DeleteAsync",
    "RelativePath": "api/DocumentType/{id}",
    "HttpMethod": "DELETE",
    "IsController": true,
    "Order": 0,
    "Parameters": [
      {
        "Name": "id",
        "Type": "System.Int32",
        "IsRequired": true
      }
    ],
    "ReturnTypes": []
  },
  {
    "ContainingType": "NeoFilm.Backend.Controllers.FilmController",
    "Method": "GetAsync",
    "RelativePath": "api/Film",
    "HttpMethod": "GET",
    "IsController": true,
    "Order": 0,
    "Parameters": [],
    "ReturnTypes": []
  },
  {
    "ContainingType": "NeoFilm.Backend.Controllers.GenericController\u00601[[NeoFilm.Shared.Entities.Film, NeoFilm.Shared, Version=1.0.0.0, Culture=neutral, PublicKeyToken=null]]",
    "Method": "PostAsync",
    "RelativePath": "api/Film",
    "HttpMethod": "POST",
    "IsController": true,
    "Order": 0,
    "Parameters": [
      {
        "Name": "model",
        "Type": "NeoFilm.Shared.Entities.Film",
        "IsRequired": true
      }
    ],
    "ReturnTypes": []
  },
  {
    "ContainingType": "NeoFilm.Backend.Controllers.GenericController\u00601[[NeoFilm.Shared.Entities.Film, NeoFilm.Shared, Version=1.0.0.0, Culture=neutral, PublicKeyToken=null]]",
    "Method": "PutAsync",
    "RelativePath": "api/Film",
    "HttpMethod": "PUT",
    "IsController": true,
    "Order": 0,
    "Parameters": [
      {
        "Name": "model",
        "Type": "NeoFilm.Shared.Entities.Film",
        "IsRequired": true
      }
    ],
    "ReturnTypes": []
  },
  {
    "ContainingType": "NeoFilm.Backend.Controllers.FilmController",
    "Method": "GetAsync",
    "RelativePath": "api/Film/{id}",
    "HttpMethod": "GET",
    "IsController": true,
    "Order": 0,
    "Parameters": [
      {
        "Name": "id",
        "Type": "System.Int32",
        "IsRequired": true
      }
    ],
    "ReturnTypes": []
  },
  {
    "ContainingType": "NeoFilm.Backend.Controllers.GenericController\u00601[[NeoFilm.Shared.Entities.Film, NeoFilm.Shared, Version=1.0.0.0, Culture=neutral, PublicKeyToken=null]]",
    "Method": "DeleteAsync",
    "RelativePath": "api/Film/{id}",
    "HttpMethod": "DELETE",
    "IsController": true,
    "Order": 0,
    "Parameters": [
      {
        "Name": "id",
        "Type": "System.Int32",
        "IsRequired": true
      }
    ],
    "ReturnTypes": []
  },
  {
    "ContainingType": "NeoFilm.Backend.Controllers.FormatController",
    "Method": "GetAsync",
    "RelativePath": "api/Format",
    "HttpMethod": "GET",
    "IsController": true,
    "Order": 0,
    "Parameters": [],
    "ReturnTypes": []
  },
  {
    "ContainingType": "NeoFilm.Backend.Controllers.GenericController\u00601[[NeoFilm.Shared.Entities.Format, NeoFilm.Shared, Version=1.0.0.0, Culture=neutral, PublicKeyToken=null]]",
    "Method": "PostAsync",
    "RelativePath": "api/Format",
    "HttpMethod": "POST",
    "IsController": true,
    "Order": 0,
    "Parameters": [
      {
        "Name": "model",
        "Type": "NeoFilm.Shared.Entities.Format",
        "IsRequired": true
      }
    ],
    "ReturnTypes": []
  },
  {
    "ContainingType": "NeoFilm.Backend.Controllers.GenericController\u00601[[NeoFilm.Shared.Entities.Format, NeoFilm.Shared, Version=1.0.0.0, Culture=neutral, PublicKeyToken=null]]",
    "Method": "PutAsync",
    "RelativePath": "api/Format",
    "HttpMethod": "PUT",
    "IsController": true,
    "Order": 0,
    "Parameters": [
      {
        "Name": "model",
        "Type": "NeoFilm.Shared.Entities.Format",
        "IsRequired": true
      }
    ],
    "ReturnTypes": []
  },
  {
    "ContainingType": "NeoFilm.Backend.Controllers.FormatController",
    "Method": "GetAsync",
    "RelativePath": "api/Format/{id}",
    "HttpMethod": "GET",
    "IsController": true,
    "Order": 0,
    "Parameters": [
      {
        "Name": "id",
        "Type": "System.Int32",
        "IsRequired": true
      }
    ],
    "ReturnTypes": []
  },
  {
    "ContainingType": "NeoFilm.Backend.Controllers.GenericController\u00601[[NeoFilm.Shared.Entities.Format, NeoFilm.Shared, Version=1.0.0.0, Culture=neutral, PublicKeyToken=null]]",
    "Method": "DeleteAsync",
    "RelativePath": "api/Format/{id}",
    "HttpMethod": "DELETE",
    "IsController": true,
    "Order": 0,
    "Parameters": [
      {
        "Name": "id",
        "Type": "System.Int32",
        "IsRequired": true
      }
    ],
    "ReturnTypes": []
  },
  {
    "ContainingType": "NeoFilm.Backend.Controllers.FunctionController",
    "Method": "PostAsync",
    "RelativePath": "api/Function",
    "HttpMethod": "POST",
    "IsController": true,
    "Order": 0,
    "Parameters": [
      {
        "Name": "function",
        "Type": "NeoFilm.Shared.Entities.Function",
        "IsRequired": true
      }
    ],
    "ReturnTypes": []
  },
  {
    "ContainingType": "NeoFilm.Backend.Controllers.GenericController\u00601[[NeoFilm.Shared.Entities.Function, NeoFilm.Shared, Version=1.0.0.0, Culture=neutral, PublicKeyToken=null]]",
    "Method": "GetAsync",
    "RelativePath": "api/Function",
    "HttpMethod": "GET",
    "IsController": true,
    "Order": 0,
    "Parameters": [],
    "ReturnTypes": []
  },
  {
    "ContainingType": "NeoFilm.Backend.Controllers.GenericController\u00601[[NeoFilm.Shared.Entities.Function, NeoFilm.Shared, Version=1.0.0.0, Culture=neutral, PublicKeyToken=null]]",
    "Method": "PutAsync",
    "RelativePath": "api/Function",
    "HttpMethod": "PUT",
    "IsController": true,
    "Order": 0,
    "Parameters": [
      {
        "Name": "model",
        "Type": "NeoFilm.Shared.Entities.Function",
        "IsRequired": true
      }
    ],
    "ReturnTypes": []
  },
  {
    "ContainingType": "NeoFilm.Backend.Controllers.GenericController\u00601[[NeoFilm.Shared.Entities.Function, NeoFilm.Shared, Version=1.0.0.0, Culture=neutral, PublicKeyToken=null]]",
    "Method": "GetAsync",
    "RelativePath": "api/Function/{id}",
    "HttpMethod": "GET",
    "IsController": true,
    "Order": 0,
    "Parameters": [
      {
        "Name": "id",
        "Type": "System.Int32",
        "IsRequired": true
      }
    ],
    "ReturnTypes": []
  },
  {
    "ContainingType": "NeoFilm.Backend.Controllers.GenericController\u00601[[NeoFilm.Shared.Entities.Function, NeoFilm.Shared, Version=1.0.0.0, Culture=neutral, PublicKeyToken=null]]",
    "Method": "DeleteAsync",
    "RelativePath": "api/Function/{id}",
    "HttpMethod": "DELETE",
    "IsController": true,
    "Order": 0,
    "Parameters": [
      {
        "Name": "id",
        "Type": "System.Int32",
        "IsRequired": true
      }
    ],
    "ReturnTypes": []
  },
  {
    "ContainingType": "NeoFilm.Backend.Controllers.MovieTheaterController",
    "Method": "GetAsync",
    "RelativePath": "api/MovieTheater",
    "HttpMethod": "GET",
    "IsController": true,
    "Order": 0,
    "Parameters": [],
    "ReturnTypes": []
  },
  {
    "ContainingType": "NeoFilm.Backend.Controllers.GenericController\u00601[[NeoFilm.Shared.Entities.MovieTheater, NeoFilm.Shared, Version=1.0.0.0, Culture=neutral, PublicKeyToken=null]]",
    "Method": "PostAsync",
    "RelativePath": "api/MovieTheater",
    "HttpMethod": "POST",
    "IsController": true,
    "Order": 0,
    "Parameters": [
      {
        "Name": "model",
        "Type": "NeoFilm.Shared.Entities.MovieTheater",
        "IsRequired": true
      }
    ],
    "ReturnTypes": []
  },
  {
    "ContainingType": "NeoFilm.Backend.Controllers.GenericController\u00601[[NeoFilm.Shared.Entities.MovieTheater, NeoFilm.Shared, Version=1.0.0.0, Culture=neutral, PublicKeyToken=null]]",
    "Method": "PutAsync",
    "RelativePath": "api/MovieTheater",
    "HttpMethod": "PUT",
    "IsController": true,
    "Order": 0,
    "Parameters": [
      {
        "Name": "model",
        "Type": "NeoFilm.Shared.Entities.MovieTheater",
        "IsRequired": true
      }
    ],
    "ReturnTypes": []
  },
  {
    "ContainingType": "NeoFilm.Backend.Controllers.MovieTheaterController",
    "Method": "GetAsync",
    "RelativePath": "api/MovieTheater/{id}",
    "HttpMethod": "GET",
    "IsController": true,
    "Order": 0,
    "Parameters": [
      {
        "Name": "id",
        "Type": "System.Int32",
        "IsRequired": true
      }
    ],
    "ReturnTypes": []
  },
  {
    "ContainingType": "NeoFilm.Backend.Controllers.GenericController\u00601[[NeoFilm.Shared.Entities.MovieTheater, NeoFilm.Shared, Version=1.0.0.0, Culture=neutral, PublicKeyToken=null]]",
    "Method": "DeleteAsync",
    "RelativePath": "api/MovieTheater/{id}",
    "HttpMethod": "DELETE",
    "IsController": true,
    "Order": 0,
    "Parameters": [
      {
        "Name": "id",
        "Type": "System.Int32",
        "IsRequired": true
      }
    ],
    "ReturnTypes": []
  },
  {
    "ContainingType": "NeoFilm.Backend.Controllers.GenericController\u00601[[NeoFilm.Shared.Entities.Payments, NeoFilm.Shared, Version=1.0.0.0, Culture=neutral, PublicKeyToken=null]]",
    "Method": "GetAsync",
    "RelativePath": "api/Payments",
    "HttpMethod": "GET",
    "IsController": true,
    "Order": 0,
    "Parameters": [],
    "ReturnTypes": []
  },
  {
    "ContainingType": "NeoFilm.Backend.Controllers.GenericController\u00601[[NeoFilm.Shared.Entities.Payments, NeoFilm.Shared, Version=1.0.0.0, Culture=neutral, PublicKeyToken=null]]",
    "Method": "PostAsync",
    "RelativePath": "api/Payments",
    "HttpMethod": "POST",
    "IsController": true,
    "Order": 0,
    "Parameters": [
      {
        "Name": "model",
        "Type": "NeoFilm.Shared.Entities.Payments",
        "IsRequired": true
      }
    ],
    "ReturnTypes": []
  },
  {
    "ContainingType": "NeoFilm.Backend.Controllers.GenericController\u00601[[NeoFilm.Shared.Entities.Payments, NeoFilm.Shared, Version=1.0.0.0, Culture=neutral, PublicKeyToken=null]]",
    "Method": "PutAsync",
    "RelativePath": "api/Payments",
    "HttpMethod": "PUT",
    "IsController": true,
    "Order": 0,
    "Parameters": [
      {
        "Name": "model",
        "Type": "NeoFilm.Shared.Entities.Payments",
        "IsRequired": true
      }
    ],
    "ReturnTypes": []
  },
  {
    "ContainingType": "NeoFilm.Backend.Controllers.GenericController\u00601[[NeoFilm.Shared.Entities.Payments, NeoFilm.Shared, Version=1.0.0.0, Culture=neutral, PublicKeyToken=null]]",
    "Method": "GetAsync",
    "RelativePath": "api/Payments/{id}",
    "HttpMethod": "GET",
    "IsController": true,
    "Order": 0,
    "Parameters": [
      {
        "Name": "id",
        "Type": "System.Int32",
        "IsRequired": true
      }
    ],
    "ReturnTypes": []
  },
  {
    "ContainingType": "NeoFilm.Backend.Controllers.GenericController\u00601[[NeoFilm.Shared.Entities.Payments, NeoFilm.Shared, Version=1.0.0.0, Culture=neutral, PublicKeyToken=null]]",
    "Method": "DeleteAsync",
    "RelativePath": "api/Payments/{id}",
    "HttpMethod": "DELETE",
    "IsController": true,
    "Order": 0,
    "Parameters": [
      {
        "Name": "id",
        "Type": "System.Int32",
        "IsRequired": true
      }
    ],
    "ReturnTypes": []
  },
  {
    "ContainingType": "NeoFilm.Backend.Controllers.RoleController",
    "Method": "GetAsync",
    "RelativePath": "api/Role",
    "HttpMethod": "GET",
    "IsController": true,
    "Order": 0,
    "Parameters": [],
    "ReturnTypes": []
  },
  {
    "ContainingType": "NeoFilm.Backend.Controllers.GenericController\u00601[[NeoFilm.Shared.Entities.Role, NeoFilm.Shared, Version=1.0.0.0, Culture=neutral, PublicKeyToken=null]]",
    "Method": "PostAsync",
    "RelativePath": "api/Role",
    "HttpMethod": "POST",
    "IsController": true,
    "Order": 0,
    "Parameters": [
      {
        "Name": "model",
        "Type": "NeoFilm.Shared.Entities.Role",
        "IsRequired": true
      }
    ],
    "ReturnTypes": []
  },
  {
    "ContainingType": "NeoFilm.Backend.Controllers.GenericController\u00601[[NeoFilm.Shared.Entities.Role, NeoFilm.Shared, Version=1.0.0.0, Culture=neutral, PublicKeyToken=null]]",
    "Method": "PutAsync",
    "RelativePath": "api/Role",
    "HttpMethod": "PUT",
    "IsController": true,
    "Order": 0,
    "Parameters": [
      {
        "Name": "model",
        "Type": "NeoFilm.Shared.Entities.Role",
        "IsRequired": true
      }
    ],
    "ReturnTypes": []
  },
  {
    "ContainingType": "NeoFilm.Backend.Controllers.RoleController",
    "Method": "GetAsync",
    "RelativePath": "api/Role/{id}",
    "HttpMethod": "GET",
    "IsController": true,
    "Order": 0,
    "Parameters": [
      {
        "Name": "id",
        "Type": "System.Int32",
        "IsRequired": true
      }
    ],
    "ReturnTypes": []
  },
  {
    "ContainingType": "NeoFilm.Backend.Controllers.GenericController\u00601[[NeoFilm.Shared.Entities.Role, NeoFilm.Shared, Version=1.0.0.0, Culture=neutral, PublicKeyToken=null]]",
    "Method": "DeleteAsync",
    "RelativePath": "api/Role/{id}",
    "HttpMethod": "DELETE",
    "IsController": true,
    "Order": 0,
    "Parameters": [
      {
        "Name": "id",
        "Type": "System.Int32",
        "IsRequired": true
      }
    ],
    "ReturnTypes": []
  },
  {
    "ContainingType": "NeoFilm.Backend.Controllers.GenericController\u00601[[NeoFilm.Shared.Entities.Seat, NeoFilm.Shared, Version=1.0.0.0, Culture=neutral, PublicKeyToken=null]]",
    "Method": "GetAsync",
    "RelativePath": "api/Seat",
    "HttpMethod": "GET",
    "IsController": true,
    "Order": 0,
    "Parameters": [],
    "ReturnTypes": []
  },
  {
    "ContainingType": "NeoFilm.Backend.Controllers.GenericController\u00601[[NeoFilm.Shared.Entities.Seat, NeoFilm.Shared, Version=1.0.0.0, Culture=neutral, PublicKeyToken=null]]",
    "Method": "PostAsync",
    "RelativePath": "api/Seat",
    "HttpMethod": "POST",
    "IsController": true,
    "Order": 0,
    "Parameters": [
      {
        "Name": "model",
        "Type": "NeoFilm.Shared.Entities.Seat",
        "IsRequired": true
      }
    ],
    "ReturnTypes": []
  },
  {
    "ContainingType": "NeoFilm.Backend.Controllers.GenericController\u00601[[NeoFilm.Shared.Entities.Seat, NeoFilm.Shared, Version=1.0.0.0, Culture=neutral, PublicKeyToken=null]]",
    "Method": "PutAsync",
    "RelativePath": "api/Seat",
    "HttpMethod": "PUT",
    "IsController": true,
    "Order": 0,
    "Parameters": [
      {
        "Name": "model",
        "Type": "NeoFilm.Shared.Entities.Seat",
        "IsRequired": true
      }
    ],
    "ReturnTypes": []
  },
  {
    "ContainingType": "NeoFilm.Backend.Controllers.GenericController\u00601[[NeoFilm.Shared.Entities.Seat, NeoFilm.Shared, Version=1.0.0.0, Culture=neutral, PublicKeyToken=null]]",
    "Method": "GetAsync",
    "RelativePath": "api/Seat/{id}",
    "HttpMethod": "GET",
    "IsController": true,
    "Order": 0,
    "Parameters": [
      {
        "Name": "id",
        "Type": "System.Int32",
        "IsRequired": true
      }
    ],
    "ReturnTypes": []
  },
  {
    "ContainingType": "NeoFilm.Backend.Controllers.GenericController\u00601[[NeoFilm.Shared.Entities.Seat, NeoFilm.Shared, Version=1.0.0.0, Culture=neutral, PublicKeyToken=null]]",
    "Method": "DeleteAsync",
    "RelativePath": "api/Seat/{id}",
    "HttpMethod": "DELETE",
    "IsController": true,
    "Order": 0,
    "Parameters": [
      {
        "Name": "id",
        "Type": "System.Int32",
        "IsRequired": true
      }
    ],
    "ReturnTypes": []
  },
  {
    "ContainingType": "NeoFilm.Backend.Controllers.SnacksController",
    "Method": "PostAsync",
    "RelativePath": "api/Snacks",
    "HttpMethod": "POST",
    "IsController": true,
    "Order": 0,
    "Parameters": [
      {
        "Name": "snack",
        "Type": "NeoFilm.Shared.Entities.Snacks",
        "IsRequired": true
      }
    ],
    "ReturnTypes": []
  },
  {
    "ContainingType": "NeoFilm.Backend.Controllers.GenericController\u00601[[NeoFilm.Shared.Entities.Snacks, NeoFilm.Shared, Version=1.0.0.0, Culture=neutral, PublicKeyToken=null]]",
    "Method": "GetAsync",
    "RelativePath": "api/Snacks",
    "HttpMethod": "GET",
    "IsController": true,
    "Order": 0,
    "Parameters": [],
    "ReturnTypes": []
  },
  {
    "ContainingType": "NeoFilm.Backend.Controllers.GenericController\u00601[[NeoFilm.Shared.Entities.Snacks, NeoFilm.Shared, Version=1.0.0.0, Culture=neutral, PublicKeyToken=null]]",
    "Method": "PutAsync",
    "RelativePath": "api/Snacks",
    "HttpMethod": "PUT",
    "IsController": true,
    "Order": 0,
    "Parameters": [
      {
        "Name": "model",
        "Type": "NeoFilm.Shared.Entities.Snacks",
        "IsRequired": true
      }
    ],
    "ReturnTypes": []
  },
  {
    "ContainingType": "NeoFilm.Backend.Controllers.GenericController\u00601[[NeoFilm.Shared.Entities.Snacks, NeoFilm.Shared, Version=1.0.0.0, Culture=neutral, PublicKeyToken=null]]",
    "Method": "GetAsync",
    "RelativePath": "api/Snacks/{id}",
    "HttpMethod": "GET",
    "IsController": true,
    "Order": 0,
    "Parameters": [
      {
        "Name": "id",
        "Type": "System.Int32",
        "IsRequired": true
      }
    ],
    "ReturnTypes": []
  },
  {
    "ContainingType": "NeoFilm.Backend.Controllers.GenericController\u00601[[NeoFilm.Shared.Entities.Snacks, NeoFilm.Shared, Version=1.0.0.0, Culture=neutral, PublicKeyToken=null]]",
    "Method": "DeleteAsync",
    "RelativePath": "api/Snacks/{id}",
    "HttpMethod": "DELETE",
    "IsController": true,
    "Order": 0,
    "Parameters": [
      {
        "Name": "id",
        "Type": "System.Int32",
        "IsRequired": true
      }
    ],
    "ReturnTypes": []
  },
  {
    "ContainingType": "NeoFilm.Backend.Controllers.SnacksDetailController",
    "Method": "GetAsync",
    "RelativePath": "api/SnacksDetail",
    "HttpMethod": "GET",
    "IsController": true,
    "Order": 0,
    "Parameters": [],
    "ReturnTypes": []
  },
  {
    "ContainingType": "NeoFilm.Backend.Controllers.GenericController\u00601[[NeoFilm.Shared.Entities.SnacksDetail, NeoFilm.Shared, Version=1.0.0.0, Culture=neutral, PublicKeyToken=null]]",
    "Method": "PostAsync",
    "RelativePath": "api/SnacksDetail",
    "HttpMethod": "POST",
    "IsController": true,
    "Order": 0,
    "Parameters": [
      {
        "Name": "model",
        "Type": "NeoFilm.Shared.Entities.SnacksDetail",
        "IsRequired": true
      }
    ],
    "ReturnTypes": []
  },
  {
    "ContainingType": "NeoFilm.Backend.Controllers.GenericController\u00601[[NeoFilm.Shared.Entities.SnacksDetail, NeoFilm.Shared, Version=1.0.0.0, Culture=neutral, PublicKeyToken=null]]",
    "Method": "PutAsync",
    "RelativePath": "api/SnacksDetail",
    "HttpMethod": "PUT",
    "IsController": true,
    "Order": 0,
    "Parameters": [
      {
        "Name": "model",
        "Type": "NeoFilm.Shared.Entities.SnacksDetail",
        "IsRequired": true
      }
    ],
    "ReturnTypes": []
  },
  {
    "ContainingType": "NeoFilm.Backend.Controllers.SnacksDetailController",
    "Method": "GetAsync",
    "RelativePath": "api/SnacksDetail/{id}",
    "HttpMethod": "GET",
    "IsController": true,
    "Order": 0,
    "Parameters": [
      {
        "Name": "id",
        "Type": "System.Int32",
        "IsRequired": true
      }
    ],
    "ReturnTypes": []
  },
  {
    "ContainingType": "NeoFilm.Backend.Controllers.GenericController\u00601[[NeoFilm.Shared.Entities.SnacksDetail, NeoFilm.Shared, Version=1.0.0.0, Culture=neutral, PublicKeyToken=null]]",
    "Method": "DeleteAsync",
    "RelativePath": "api/SnacksDetail/{id}",
    "HttpMethod": "DELETE",
    "IsController": true,
    "Order": 0,
    "Parameters": [
      {
        "Name": "id",
        "Type": "System.Int32",
        "IsRequired": true
      }
    ],
    "ReturnTypes": []
  },
  {
    "ContainingType": "NeoFilm.Backend.Controllers.SnacksDetailController",
    "Method": "PostAsync",
    "RelativePath": "api/SnacksDetail/CreateWithDto",
    "HttpMethod": "POST",
    "IsController": true,
    "Order": 0,
    "Parameters": [
      {
        "Name": "dto",
        "Type": "NeoFilm.Shared.Dtos.SnacksDetailDTO",
        "IsRequired": true
      }
    ],
    "ReturnTypes": []
  },
  {
    "ContainingType": "NeoFilm.Backend.Controllers.TemporalCarController",
    "Method": "GetAsync",
    "RelativePath": "api/TemporalCar",
    "HttpMethod": "GET",
    "IsController": true,
    "Order": 0,
    "Parameters": [],
    "ReturnTypes": []
  },
  {
    "ContainingType": "NeoFilm.Backend.Controllers.TemporalCarController",
    "Method": "AddSnackAsync",
    "RelativePath": "api/TemporalCar/{carritoId}/add-snack",
    "HttpMethod": "POST",
    "IsController": true,
    "Order": 0,
    "Parameters": [
      {
        "Name": "carritoId",
        "Type": "System.Int32",
        "IsRequired": true
      },
      {
        "Name": "snack",
        "Type": "NeoFilm.Shared.Dtos.SnacksDetailDTO",
        "IsRequired": true
      }
    ],
    "ReturnTypes": []
  },
  {
    "ContainingType": "NeoFilm.Backend.Controllers.TemporalCarController",
    "Method": "AddTicketAsync",
    "RelativePath": "api/TemporalCar/{carritoId}/add-ticket",
    "HttpMethod": "POST",
    "IsController": true,
    "Order": 0,
    "Parameters": [
      {
        "Name": "carritoId",
        "Type": "System.Int32",
        "IsRequired": true
      },
      {
        "Name": "ticket",
        "Type": "NeoFilm.Shared.Dtos.TicketDTO",
        "IsRequired": true
      }
    ],
    "ReturnTypes": []
  },
  {
    "ContainingType": "NeoFilm.Backend.Controllers.TemporalCarController",
    "Method": "ClearCartAsync",
    "RelativePath": "api/TemporalCar/{carritoId}/clear",
    "HttpMethod": "DELETE",
    "IsController": true,
    "Order": 0,
    "Parameters": [
      {
        "Name": "carritoId",
        "Type": "System.Int32",
        "IsRequired": true
      }
    ],
    "ReturnTypes": []
  },
  {
    "ContainingType": "NeoFilm.Backend.Controllers.TemporalCarController",
    "Method": "UpdateCartAsync",
    "RelativePath": "api/TemporalCar/{id}",
    "HttpMethod": "PUT",
    "IsController": true,
    "Order": 0,
    "Parameters": [
      {
        "Name": "id",
        "Type": "System.Int32",
        "IsRequired": true
      },
      {
        "Name": "model",
        "Type": "NeoFilm.Shared.Entities.TemporalCar",
        "IsRequired": true
      }
    ],
    "ReturnTypes": []
  },
  {
    "ContainingType": "NeoFilm.Backend.Controllers.TemporalCarController",
    "Method": "CreateBillAsync",
    "RelativePath": "api/TemporalCar/crear orden",
    "HttpMethod": "POST",
    "IsController": true,
    "Order": 0,
    "Parameters": [
      {
        "Name": "carritoId",
        "Type": "System.Int32",
        "IsRequired": false
      },
      {
        "Name": "paymentId",
        "Type": "System.Int32",
        "IsRequired": false
      }
    ],
    "ReturnTypes": []
  },
  {
    "ContainingType": "NeoFilm.Backend.Controllers.TicketController",
    "Method": "GetAsync",
    "RelativePath": "api/Ticket",
    "HttpMethod": "GET",
    "IsController": true,
    "Order": 0,
    "Parameters": [],
    "ReturnTypes": []
  },
  {
    "ContainingType": "NeoFilm.Backend.Controllers.GenericController\u00601[[NeoFilm.Shared.Entities.Ticket, NeoFilm.Shared, Version=1.0.0.0, Culture=neutral, PublicKeyToken=null]]",
    "Method": "PostAsync",
    "RelativePath": "api/Ticket",
    "HttpMethod": "POST",
    "IsController": true,
    "Order": 0,
    "Parameters": [
      {
        "Name": "model",
        "Type": "NeoFilm.Shared.Entities.Ticket",
        "IsRequired": true
      }
    ],
    "ReturnTypes": []
  },
  {
    "ContainingType": "NeoFilm.Backend.Controllers.GenericController\u00601[[NeoFilm.Shared.Entities.Ticket, NeoFilm.Shared, Version=1.0.0.0, Culture=neutral, PublicKeyToken=null]]",
    "Method": "PutAsync",
    "RelativePath": "api/Ticket",
    "HttpMethod": "PUT",
    "IsController": true,
    "Order": 0,
    "Parameters": [
      {
        "Name": "model",
        "Type": "NeoFilm.Shared.Entities.Ticket",
        "IsRequired": true
      }
    ],
    "ReturnTypes": []
  },
  {
    "ContainingType": "NeoFilm.Backend.Controllers.TicketController",
    "Method": "GetAsync",
    "RelativePath": "api/Ticket/{id}",
    "HttpMethod": "GET",
    "IsController": true,
    "Order": 0,
    "Parameters": [
      {
        "Name": "id",
        "Type": "System.Int32",
        "IsRequired": true
      }
    ],
    "ReturnTypes": []
  },
  {
    "ContainingType": "NeoFilm.Backend.Controllers.TicketController",
    "Method": "DeleteAsync",
    "RelativePath": "api/Ticket/{id}",
    "HttpMethod": "DELETE",
    "IsController": true,
    "Order": 0,
    "Parameters": [
      {
        "Name": "id",
        "Type": "System.Int32",
        "IsRequired": true
      }
    ],
    "ReturnTypes": []
  },
  {
    "ContainingType": "NeoFilm.Backend.Controllers.TicketController",
    "Method": "PostAsync",
    "RelativePath": "api/Ticket/DTO",
    "HttpMethod": "POST",
    "IsController": true,
    "Order": 0,
    "Parameters": [
      {
        "Name": "dto",
        "Type": "NeoFilm.Shared.Dtos.TicketDTO",
        "IsRequired": true
      }
    ],
    "ReturnTypes": []
  },
  {
    "ContainingType": "NeoFilm.Backend.Controllers.UserController",
    "Method": "PostAsync",
    "RelativePath": "api/User",
    "HttpMethod": "POST",
    "IsController": true,
    "Order": 0,
    "Parameters": [
      {
        "Name": "user",
        "Type": "NeoFilm.Shared.Entities.User",
        "IsRequired": true
      }
    ],
    "ReturnTypes": []
  },
  {
    "ContainingType": "NeoFilm.Backend.Controllers.GenericController\u00601[[NeoFilm.Shared.Entities.User, NeoFilm.Shared, Version=1.0.0.0, Culture=neutral, PublicKeyToken=null]]",
    "Method": "GetAsync",
    "RelativePath": "api/User",
    "HttpMethod": "GET",
    "IsController": true,
    "Order": 0,
    "Parameters": [],
    "ReturnTypes": []
  },
  {
    "ContainingType": "NeoFilm.Backend.Controllers.GenericController\u00601[[NeoFilm.Shared.Entities.User, NeoFilm.Shared, Version=1.0.0.0, Culture=neutral, PublicKeyToken=null]]",
    "Method": "PutAsync",
    "RelativePath": "api/User",
    "HttpMethod": "PUT",
    "IsController": true,
    "Order": 0,
    "Parameters": [
      {
        "Name": "model",
        "Type": "NeoFilm.Shared.Entities.User",
        "IsRequired": true
      }
    ],
    "ReturnTypes": []
  },
  {
    "ContainingType": "NeoFilm.Backend.Controllers.GenericController\u00601[[NeoFilm.Shared.Entities.User, NeoFilm.Shared, Version=1.0.0.0, Culture=neutral, PublicKeyToken=null]]",
    "Method": "GetAsync",
    "RelativePath": "api/User/{id}",
    "HttpMethod": "GET",
    "IsController": true,
    "Order": 0,
    "Parameters": [
      {
        "Name": "id",
        "Type": "System.Int32",
        "IsRequired": true
      }
    ],
    "ReturnTypes": []
  },
  {
    "ContainingType": "NeoFilm.Backend.Controllers.GenericController\u00601[[NeoFilm.Shared.Entities.User, NeoFilm.Shared, Version=1.0.0.0, Culture=neutral, PublicKeyToken=null]]",
    "Method": "DeleteAsync",
    "RelativePath": "api/User/{id}",
    "HttpMethod": "DELETE",
    "IsController": true,
    "Order": 0,
    "Parameters": [
      {
        "Name": "id",
        "Type": "System.Int32",
        "IsRequired": true
      }
    ],
    "ReturnTypes": []
  },
  {
    "ContainingType": "NeoFilm.Backend.Controllers.VenuesController",
    "Method": "GetAsync",
    "RelativePath": "api/Venues",
    "HttpMethod": "GET",
    "IsController": true,
    "Order": 0,
    "Parameters": [],
    "ReturnTypes": []
  },
  {
    "ContainingType": "NeoFilm.Backend.Controllers.GenericController\u00601[[NeoFilm.Shared.Entities.Venue, NeoFilm.Shared, Version=1.0.0.0, Culture=neutral, PublicKeyToken=null]]",
    "Method": "PostAsync",
    "RelativePath": "api/Venues",
    "HttpMethod": "POST",
    "IsController": true,
    "Order": 0,
    "Parameters": [
      {
        "Name": "model",
        "Type": "NeoFilm.Shared.Entities.Venue",
        "IsRequired": true
      }
    ],
    "ReturnTypes": []
  },
  {
    "ContainingType": "NeoFilm.Backend.Controllers.GenericController\u00601[[NeoFilm.Shared.Entities.Venue, NeoFilm.Shared, Version=1.0.0.0, Culture=neutral, PublicKeyToken=null]]",
    "Method": "PutAsync",
    "RelativePath": "api/Venues",
    "HttpMethod": "PUT",
    "IsController": true,
    "Order": 0,
    "Parameters": [
      {
        "Name": "model",
        "Type": "NeoFilm.Shared.Entities.Venue",
        "IsRequired": true
      }
    ],
    "ReturnTypes": []
  },
  {
    "ContainingType": "NeoFilm.Backend.Controllers.VenuesController",
    "Method": "GetAsync",
    "RelativePath": "api/Venues/{id}",
    "HttpMethod": "GET",
    "IsController": true,
    "Order": 0,
    "Parameters": [
      {
        "Name": "id",
        "Type": "System.Int32",
        "IsRequired": true
      }
    ],
    "ReturnTypes": []
  },
  {
    "ContainingType": "NeoFilm.Backend.Controllers.GenericController\u00601[[NeoFilm.Shared.Entities.Venue, NeoFilm.Shared, Version=1.0.0.0, Culture=neutral, PublicKeyToken=null]]",
    "Method": "DeleteAsync",
    "RelativePath": "api/Venues/{id}",
    "HttpMethod": "DELETE",
    "IsController": true,
    "Order": 0,
    "Parameters": [
      {
        "Name": "id",
        "Type": "System.Int32",
        "IsRequired": true
      }
    ],
    "ReturnTypes": []
  }
]